sharp_cocoro/__init__.py
sharp_cocoro/cocoro.py
sharp_cocoro/device.py
sharp_cocoro/http_adapter.py
sharp_cocoro/properties.py
sharp_cocoro/py.typed
sharp_cocoro/response_types.py
sharp_cocoro/state.py
sharp_cocoro/state8_fixed.py
sharp_cocoro/devices/__init__.py
sharp_cocoro/devices/unknown.py
sharp_cocoro/devices/aircon/__init__.py
sharp_cocoro/devices/aircon/aircon.py
sharp_cocoro/devices/aircon/aircon_properties.py
sharp_cocoro/devices/purifier/__init__.py
sharp_cocoro/devices/purifier/purifier.py
sharp_cocoro/devices/purifier/purifier_properties.py
sharp_cocoro-0.2.3.dist-info/METADATA
sharp_cocoro-0.2.3.dist-info/WHEEL
sharp_cocoro-0.2.3.dist-info/RECORD
