Metadata-Version: 2.4
Name: sharp-cocoro
Version: 0.2.3
Summary: A Python SDK for the Cocoro API
Project-URL: Homepage, https://github.com/dvcrn/sharp-cocoro
Project-URL: Repository, https://github.com/dvcrn/sharp-cocoro
Author-email: David Mohl <git@d.sh>
License: MIT
Requires-Python: >=3.8
Requires-Dist: httpx>=0.27.0
Provides-Extra: dev
Requires-Dist: mypy; extra == 'dev'
Requires-Dist: pytest; extra == 'dev'
Requires-Dist: ruff; extra == 'dev'
